scrapy_sticky_meta_params/__init__.py
scrapy_sticky_meta_params/middleware.py
scrapy_sticky_meta_params-1.0.0.dist-info/LICENSE
scrapy_sticky_meta_params-1.0.0.dist-info/METADATA
scrapy_sticky_meta_params-1.0.0.dist-info/WHEEL
scrapy_sticky_meta_params-1.0.0.dist-info/top_level.txt
scrapy_sticky_meta_params-1.0.0.dist-info/RECORD
