Metadata-Version: 2.1
Name: scrapy-sticky-meta-params
Version: 1.0.0
Summary: A spider middleware that forwards meta params through subsequent requests.
Home-page: https://github.com/heylouiz/scrapy-sticky-meta-params
Author: Luiz Francisco Rodrigues da Silva
Author-email: luizfrdasilva@gmail.com
License: MIT license
Keywords: scrapy meta middleware
Platform: Any
Classifier: Intended Audience :: Developers
Classifier: License :: OSI Approved :: MIT License
Classifier: Natural Language :: English
Classifier: Programming Language :: Python :: 3
Classifier: Programming Language :: Python :: 3.4
Classifier: Programming Language :: Python :: 3.5
Classifier: Programming Language :: Python :: 3.6
Classifier: Programming Language :: Python :: 3.7
Classifier: Programming Language :: Python :: 3.8
Classifier: Programming Language :: Python :: 3.9
License-File: LICENSE
Requires-Dist: Scrapy (>=1.6.0)
